smolu/__init__.py
smolu/__main__.py
smolu/config.py
smolu/gen.py
smolu/state.py
smolu-0.4.0.dist-info/licenses/LICENCE
smolu-0.4.0.dist-info/METADATA
smolu-0.4.0.dist-info/WHEEL
smolu-0.4.0.dist-info/entry_points.txt
smolu-0.4.0.dist-info/top_level.txt
smolu-0.4.0.dist-info/RECORD
