Metadata-Version: 2.4
Name: smolu
Version: 0.4.0
Summary: File-based url shortener to self-host
Author-email: Théo Cavignac <theo.cavignac@gmail.com>
License-Expression: BSD-3-Clause
Project-URL: repository, https://git.sr.ht/~lattay/smolu
Project-URL: homepage, https://git.sr.ht/~lattay/smolu
License-File: LICENCE
Dynamic: license-file
